README.rst
setup.py
pyotsu.egg-info/PKG-INFO
pyotsu.egg-info/SOURCES.txt
pyotsu.egg-info/dependency_links.txt
pyotsu.egg-info/top_level.txt
src/pyotsu/__init__.py