Metadata-Version: 1.0
Name: pyotsu
Version: 0.0.3
Summary: Python Open Text Search Utility
Home-page: http://com.nicovideo.jp/community/co1995667
Author: Kenboo
Author-email: kenbooing@gmail.com
License: UNKNOWN
Platform: UNKNOWN
Classifier: Development Status :: 1 - Planning
Classifier: Environment :: Console
Classifier: Intended Audience :: Developers
Classifier: License :: OSI Approved :: Python Software Foundation License
Classifier: Operating System :: MacOS :: MacOS X
Classifier: Operating System :: Microsoft :: Windows
Classifier: Operating System :: POSIX
Classifier: Programming Language :: Python
Classifier: Topic :: Software Development 
